Workbook

Sheet Inputs
A1: ACKINDEX GOVERNMENT CONTRACT PRICING MODEL
A3: 📝 INSTRUCTIONS: Edit YELLOW cells to update all calculations
A5: VOLUME ASSUMPTIONS
A6: Monthly Footage (minutes) | B6: 5000 | C6: min/month | D6: Benchmark: 5,000 min = 83.3 hours
A7: Monthly Queries | B7: 5000 | C7: queries/month | D7: User questions per month
A8: Storage per Minute (MB) | B8: 125 | C8: MB | D8: Compressed video storage
A9: Monthly Bandwidth (GB) | B9: 500 | C9: GB | D9: CDN streaming to users
A11: INFRASTRUCTURE UNIT COSTS
A12: Supabase Pro (monthly) | B12: 25 | C12: $/month | D12: PostgreSQL + pgvector database
A13: Vercel Pro (monthly) | B13: 20 | C13: $/month | D13: Next.js hosting
A14: Upstash Redis (monthly) | B14: 0 | C14: $/month | D14: Free tier caching
A15: Sentry (monthly) | B15: 0 | C15: $/month | D15: Free tier monitoring
A17: STORAGE UNIT COSTS
A18: Bunny.net Storage | B18: 0.005 | C18: $/GB/month | D18: Video file storage
A19: Bunny.net Bandwidth | B19: 0.01 | C19: $/GB | D19: CDN streaming
A21: TRANSCRIPTION UNIT COSTS
A22: AssemblyAI (per minute) | B22: 0.0222 | C22: $/min | D22: Primary - best quality
A23: Gladia Nova-2 (per minute) | B23: 0.0043 | C23: $/min | D23: Alternative - budget
A25: AI SERVICE UNIT COSTS
A26: Voyage AI Embeddings | B26: 0.06 | C26: $/1M tokens | D26: Semantic search vectors
A27: Claude Haiku Input | B27: 0.8 | C27: $/1M tokens | D27: Simple queries
A28: Claude Haiku Output | B28: 4 | C28: $/1M tokens | D28: Simple responses
A29: Claude Sonnet Input | B29: 3 | C29: $/1M tokens | D29: Complex queries
A30: Claude Sonnet Output | B30: 15 | C30: $/1M tokens | D30: Complex responses
A31: Haiku Query Percentage | B31: 0.8 | C31: % | D31: % of queries using Haiku
A32: Tokens per Query (input) | B32: 800 | C32: tokens | D32: Average input tokens
A33: Tokens per Query (output) | B33: 400 | C33: tokens | D33: Average output tokens
A34: Tokens per Minute (embedding) | B34: 150 | C34: tokens | D34: For new content
A36: ONE-TIME SETUP COSTS
A37: Professional Services Rate | B37: 150 | C37: $/hour | D37: Integration & customization
A38: Professional Services Hours | B38: 40 | C38: hours | D38: Estimated setup time
A39: Training Rate | B39: 250 | C39: $/hour | D39: Staff training
A40: Training Hours | B40: 8 | C40: hours | D40: Admin + user training
A42: MARKUP & MARGIN SETTINGS
A43: GSA Schedule Markup | B43: 0.15 | C43: % | D43: Standard 15% government markup
A44: Target Gross Margin | B44: 0.5 | C44: % | D44: Target profit margin on pricing

Sheet Cost Breakdown
A1: MONTHLY COST BREAKDOWN
A3: Component | B3: Monthly Cost | C3: Annual Cost | D3: % of Total | E3: Formula Reference
A4: INFRASTRUCTURE
A5: Supabase Pro | B5: =Inputs!B10 | C5: =B5*12 | E5: Database
A6: Vercel Pro | B6: =Inputs!B11 | C6: =B6*12 | E6: Hosting
A7: Upstash Redis | B7: =Inputs!B12 | C7: =B7*12 | E7: Caching
A8: Sentry | B8: =Inputs!B13 | C8: =B8*12 | E8: Monitoring
A9: Infrastructure Subtotal | B9: =SUM(B5:B8) | C9: =B9*12
A11: STORAGE
A12: Video Storage | B12: =(Inputs!B6*Inputs!B8/1024)*Inputs!B16 | C12: =B12*12 | E12: =(minutes × MB/min ÷ 1024) × $/GB
A13: Video Bandwidth (CDN) | B13: =Inputs!B9*Inputs!B17 | C13: =B13*12 | E13: =GB × $/GB
A14: Storage Subtotal | B14: =SUM(B12:B13) | C14: =B14*12
A16: TRANSCRIPTION
A17: AssemblyAI Transcription | B17: =Inputs!B6*Inputs!B20 | C17: =B17*12 | E17: =minutes × $/min
A19: AI SERVICES
A20: Embeddings (New Content) | B20: =Inputs!B6*Inputs!B32/1000000*Inputs!B24 | C20: =B20*12 | E20: =min × tokens/min ÷ 1M × $/1M
A21: Claude Haiku (Simple Queries) | B21: =Inputs!B7*Inputs!B29*((Inputs!B30/1000000*Inputs!B25)+(Inputs!B31/1000000*Inputs!B26)) | C21: =B21*12 | E21: =queries × haiku% × token costs
A22: Claude Sonnet (Complex Queries) | B22: =Inputs!B7*(1-Inputs!B29)*((Inputs!B30/1000000*Inputs!B27)+(Inputs!B31/1000000*Inputs!B28)) | C22: =B22*12 | E22: =queries × sonnet% × token costs
A23: AI Services Subtotal | B23: =SUM(B20:B22) | C23: =B23*12
A25: TOTAL MONTHLY OPERATIONS | B25: =B9+B14+B17+B23 | C25: =B25*12
A27: Cost Per Minute of Footage | B27: =B25/Inputs!B6 | E27: =Total ÷ minutes
A29: ONE-TIME SETUP COSTS
A30: Professional Services | B30: =Inputs!B35*Inputs!B36 | E30: =rate × hours
A31: Training | B31: =Inputs!B37*Inputs!B38 | E31: =rate × hours
A32: Setup Total | B32: =B30+B31
A34: WITH GSA MARKUP
A35: Monthly Operations (with markup) | B35: =B25*(1+Inputs!B41)
A36: Setup (with markup) | B36: =B32*(1+Inputs!B41)

Sheet Pricing Tiers
A1: CONTRACT PRICING TIERS
A3: SET YOUR PRICES (edit yellow cells)
A4: Tier | B4: Minutes/Month | C4: Your Price | D4: Cost | E4: Gross Profit | F4: Margin % | G4: Overage $/min | H4: Setup Fee
A5: Basic | B5: 2500 | C5: 299 | D5: ='Cost Breakdown'!B27*B5+'Cost Breakdown'!B9 | E5: =C5-D5 | F5: =IF(C5>0,E5/C5,0) | G5: 0.15 | H5: ='Cost Breakdown'!B32*(1+Inputs!B41)
A6: Standard | B6: 5000 | C6: 399 | D6: ='Cost Breakdown'!B27*B6+'Cost Breakdown'!B9 | E6: =C6-D6 | F6: =IF(C6>0,E6/C6,0) | G6: 0.13 | H6: ='Cost Breakdown'!B32*(1+Inputs!B41)
A7: Professional | B7: 10000 | C7: 699 | D7: ='Cost Breakdown'!B27*B7+'Cost Breakdown'!B9 | E7: =C7-D7 | F7: =IF(C7>0,E7/C7,0) | G7: 0.11 | H7: ='Cost Breakdown'!B32*(1+Inputs!B41)
A8: Enterprise | B8: 25000 | C8: 1499 | D8: ='Cost Breakdown'!B27*B8+'Cost Breakdown'!B9 | E8: =C8-D8 | F8: =IF(C8>0,E8/C8,0) | G8: 0.09 | H8: ='Cost Breakdown'!B32*(1+Inputs!B41)
A11: ANNUAL CONTRACT VALUES
A12: Tier | B12: Monthly Fee | C12: Annual Fee | D12: Setup | E12: Year 1 Total | F12: Year 2+ Annual | G12: Year 1 Margin | H12: Break-even Months
A13: Basic | B13: =C5 | C13: =C5*12 | D13: =H5 | E13: =C13+D13 | F13: =C13 | G13: =(C13-(D5*12))/E13 | H13: =IF(E5>0,D13/E5,0)
A14: Standard | B14: =C6 | C14: =C6*12 | D14: =H6 | E14: =C14+D14 | F14: =C14 | G14: =(C14-(D6*12))/E14 | H14: =IF(E6>0,D14/E6,0)
A15: Professional | B15: =C7 | C15: =C7*12 | D15: =H7 | E15: =C15+D15 | F15: =C15 | G15: =(C15-(D7*12))/E15 | H15: =IF(E7>0,D15/E7,0)
A16: Enterprise | B16: =C8 | C16: =C8*12 | D16: =H8 | E16: =C16+D16 | F16: =C16 | G16: =(C16-(D8*12))/E16 | H16: =IF(E8>0,D16/E8,0)

Sheet Grant Budget
A1: 3-YEAR GRANT BUDGET TEMPLATE
A3: Select Minutes Tier: | B3: 5000 | C3: min/month
A5: Line Item | B5: Year 1 | C5: Year 2 | D5: Year 3 | E5: 3-Year Total | F5: Notes
A6: Platform Setup & Integration | B6: ='Cost Breakdown'!B32*(1+Inputs!B41) | C6: 0 | D6: 0 | E6: =SUM(B6:D6) | F6: One-time
A7: Annual Platform Operations | B7: =(('Cost Breakdown'!B27*B3)+'Cost Breakdown'!B9)*12*(1+Inputs!B41) | C7: =B7 | D7: =B7 | E7: =SUM(B7:D7) | F7: =3 min/month tier
A8: Contingency (10%) | B8: =(B6+B7)*0.1 | C8: =C7*0.1 | D8: =D7*0.1 | E8: =SUM(B8:D8)
A9: GRANT TOTAL | B9: =SUM(B6:B8) | C9: =SUM(C6:C8) | D9: =SUM(D6:D8) | E9: =SUM(E6:E8)

Sheet ROI Calculator
A1: ROI ANALYSIS FOR MUNICIPALITIES
A3: MUNICIPALITY ASSUMPTIONS (edit yellow)
A4: Staff Hours Saved per Month | B4: 40 | C4: hours | D4: Answering constituent inquiries
A5: Average Staff Hourly Cost | B5: 50 | C5: $/hour | D5: Including benefits
A6: Selected Pricing Tier | B6: 5000 | C6: min/month | D6: Match to Pricing Tiers sheet
A8: CALCULATED VALUES
A9: Monthly Labor Savings | B9: =B4*B5
A10: Annual Labor Savings | B10: =B9*12
A11: Annual Platform Cost | B11: =(('Cost Breakdown'!B27*B6)+'Cost Breakdown'!B9)*12*(1+Inputs!B41)
A12: Net Annual Benefit | B12: =B10-B11
A13: ROI Percentage | B13: =IF(B11>0,B12/B11,0)
A14: Payback Period | B14: =IF(B9>0,B11/12/B9,0)
